{
      "スターデューバレーまつり": [
            "fall16_name"
      ],
      "ゲームのテントは去年ぜんぶ回っちゃった！": [
            "fall16_Abigail_spouse"
      ],
      "ロビンのテクニックは去年ぜんぶ盗んだつもりだったけど、彼女にはいっつも先を行かれちゃうな！": [
            "fall16_Leah_spouse"
      ],
      "モグモグ…バーべキューサンドイッチをおなかいっぱい食べられるのって、このお祭りくらいなんだよね。": [
            "fall16_Maru_spouse"
      ],
      "今年の町内品評会、勝てたらいいね！": [
            "fall16_Penny_spouse"
      ],
      "品評会に展示するとっておき、忘れずにもってきた？今年はわたしたちで勝ちたいね。": [
            "fall16_Haley_spouse"
      ],
      "ああ、@。おれはサムに会いに行くよ。そっちも行って楽しんでこいよ。": [
            "fall16_Sebastian_spouse"
      ],
      "セバスチャンのやつ、変わってなかったよ。そっちはどうだ、楽しんでるか？": [
            "fall16_Sam_spouse"
      ],
      "オレは昔の友だちと会ってくるよ…お前も、行って楽しんでこいよ。": [
            "fall16_Alex_spouse"
      ],
      "きみの帰る準備ができるまで、ここで待ってるよ…": [
            "fall16_Harvey_spouse"
      ],
      "こうばしい香りにさそわれてここへ来たんだけど、もうピリ辛ソースにやみつきになっちゃって…（ゴクン）": [
            "fall16_Elliott_spouse"
      ],
      "ゲームのテント、ぜ～んぶ回っちゃった。…次はなにしよっか？": [
            "fall16_Abigail"
      ],
      "木工細工の伝統って、ずっと古くからつづいてるんだ。それに加われるのはすごくほこらしいよ。": [
            "fall16_Robin"
      ],
      "ロビンはとても熱心に木工品にとりくんできたんだ…時にはちょっとくらい評価されたっていいだろう？": [
            "fall16_Demetrius"
      ],
      "（ジュルッ）うーん…このバーベキューソース、ものすごーくおいしい…": [
            "fall16_Maru"
      ],
      "きょうはさわがしくなりそうだな…しばらくはこのへんにいよう。": [
            "fall16_Sebastian"
      ],
      "ウチの店で仕入れてる品物は、谷じゅうで一番質がいいんですよ。さあさあもっと近くによって、質のよさをその目で確かめてください！": [
            "fall16_Pierre"
      ],
      "ピエールは展示のために、すごく真剣に品物を準備したの。この日のためにもう何週間も前から、見ばえがいい品物をよりすぐってたのよ。": [
            "fall16_Caroline"
      ],
      "あなたも、参加するならがんばってね！": [
            "fall16_Caroline_sv1"
      ],
      "この動物たちは、見かけで人を判断することはないんだ。これが人間だと、そうはいかないね。": [
            "fall16_Linus"
      ],
      "「ちからだめし」ゲームをやりすぎたな。腕に力が入らなくなっちまった…": [
            "fall16_Alex"
      ],
      "ふむ…くん製ターキーのもも肉か。この祭りも捨てたもんじゃないな。": [
            "fall16_George"
      ],
      "ガスがベジタリアンむけのメニューも用意してくれたらいいんだけど。ズッキーニの串焼きとか、ねえ？": [
            "fall16_Evelyn"
      ],
      "やあ@、きょうは大舞台だぞ…この「スターデューまつり」は、一年のなかで一番だいじな祭りなんだ。": [
            "fall16_Lewis"
      ],
      "そうだ、町内品評会に参加したいなら、きみのために場所をひとつ空けておいたぞ。展示場所に品物をぜんぶセットしたら声をかけてくれ。そしたら審査をはじめよう。": [
            "fall16_Lewis_sv1"
      ],
      "ときどき不満をいいたくもなるけど、それでもこの仕事はおれのほこりなんだ。": [
            "fall16_Clint"
      ],
      "きょうは一番できがいい品をもってきたんだ。きっと気にいるよ。": [
            "fall16_Clint_sv1"
      ],
      "ホントはわたしがピエロをやりたかったの。でも、期をのがしちゃって。": [
            "fall16_Emily"
      ],
      "10回つづけて幸運の輪に勝ったんだけど、そしたらお店の人がもうやらせてくれなくなったの…": [
            "fall16_Penny"
      ],
      "釣りのテントに行くんなら急ぎな、若いの…じゃないと、パムおばさんが生けすの魚を釣りつくしちまうからね！へへへ。": [
            "fall16_Pam"
      ],
      "占いの館にはもう行った？テントなら墓地に建ってるよ。": [
            "fall16_Haley"
      ],
      "わたしはもう行ったけど…すごく…おもしろかった。（ブルッ）": [
            "fall16_Haley_sv1"
      ],
      "あのピエロさん、あまりしあわせそうじゃないね…きっと、今年はルイス町長がギャラの予算を削ったのね。": [
            "fall16_Jodi"
      ],
      "あのピエロがおもしろいことをしないか、ずっと見てるんだ。": [
            "fall16_Kent"
      ],
      "いまのところ、かなりがっかりしてるよ。": [
            "fall16_Kent_sv1"
      ],
      "よう@、楽しんでるか？": [
            "fall16_Sam"
      ],
      "射撃のテントはおもしろいぜ。腕に自信があるなら、スターをたくさんかせぐにはちょうどいいかもな。": [
            "fall16_Sam_sv1"
      ],
      "ロビンの腕にはいつも関心するよ。わたしも、作品をつくるときには彼女とおなじようなテクニックを　使うからさ。": [
            "fall16_Leah"
      ],
      "こいつらはみんな人なつっこいし、マッサージされるのが大好きなんだ。": [
            "fall16_Shane"
      ],
      "ベストは尽くしたけど、わたしの展示、やっぱりピエールの展示と比べると見おとりしちゃうな。": [
            "fall16_Marnie"
      ],
      "でもあの大きな丸チーズなら、審査員からボーナス点をもらえるかも。": [
            "fall16_Marnie_sv1"
      ],
      "ガスからソースのレシピを聞き出そうとしてるんだけどね、さすが彼、口がかたいよ。": [
            "fall16_Elliott"
      ],
      "さあ、すきなだけ食べてってくれよ！きょうはぜんぶタダだ…ルイス町長にお礼を言ってくれよ。": [
            "fall16_Gus"
      ],
      "おっと！食べるときは、わたし特製ヒミツのソースをつけておくれよ。": [
            "fall16_Gus_sv1"
      ],
      "上では雨がふってるの？へぇ…": [
            "fall16_Dwarf"
      ],
      "雨かあ…伝説のなかでしか聞いたことないよ。一生雨を見ることがない仲間もいるくらい。": [
            "fall16_Dwarf_sv1"
      ],
      "ウェルウィックと我輩は古くからの知り合いでな…彼女は卓越した占い師だ。それによき友でもある。": [
            "fall16_Wizard"
      ],
      "…": [
            "fall16_Wizard_sv1"
      ],
      "あの道化師…どこかで見たような。": [
            "fall16_Wizard_sv2"
      ],
      "幻術の学舎か？それとも秘術のカーニバルだったか？ううむ…": [
            "fall16_Wizard_sv3"
      ],
      "あの道化師どこかで見たような。幻術の学舎か？それとも秘術のカーニバルだったか？ううむ": [
            "fall16_Wizard_sv4"
      ],
      "ちょっと歩けばすぐそこで、ガスがポークリブをひとそろい焼いてるんだよな…やれやれ。": [
            "fall16_Harvey"
      ],
      "いや、ちょっと自己内省をね…1": [
            "fall16_Harvey_sv1"
      ],
      "うちの方では、雨が降ってるらしいよ。だから、ここに来たの？": [
            "fall16_Sandy"
      ],
      "わたしは、ちょっと雨が恋しいな。実はね…": [
            "fall16_Sandy_sv1"
      ],
      "いたっ！めんどりが小指つついたー！": [
            "fall16_Jas"
      ],
      "モオー！モオー！": [
            "fall16_Vincent"
      ],
      "クリントの剣は年々鋭さをましているな。": [
            "fall16_Marlon"
      ],
      "値段もだが…": [
            "fall16_Marlon_sv1"
      ],
      "品評会の展示はおわったかい、@？%farm牧場でとれたいい品を、みんなに見せるチャンスだぞ！": [
            "fall16_Willy"
      ],
      "はははっ！こんなの初めて見たよ…": [
            "fall16_Leo"
      ],
      "この武器、カッコいいと思わない？ひとつ持って帰りたいな。": [
            "fall16_Abigail_spouse_y2"
      ],
      "今年はロビンがとっておきの技を教えてくれるの。": [
            "fall16_Leah_spouse_y2"
      ],
      "あとで見せてあげるね…": [
            "fall16_Leah_spouse_y2_sv1"
      ],
      "品評会ではいっしょに優勝を目指しましょう！今年もあなたはすごくがんばったんだもの。": [
            "fall16_Maru_spouse_y2"
      ],
      "いっしょに座りましょう？ちょうど2人で座れるわ。": [
            "fall16_Penny_spouse_y2"
      ],
      "アレックスが口いっぱい食べてるのはちょっとおもしろいわね。すごく元気そうだわ。": [
            "fall16_Haley_spouse_y2"
      ],
      "品評会では私たちが優勝できるといいわね！": [
            "fall16_Haley_spouse_y2_sv1"
      ],
      "サンディは今日のためにカリコ砂漠から来てくれたのよ。": [
            "fall16_Emily_spouse_y2"
      ],
      "彼女に会えるのはとってもうれしいわ！": [
            "fall16_Emily_spouse_y2_sv1"
      ],
      "墓場にいたあの女性は、オレたちの未来を予言していた…": [
            "fall16_Sebastian_spouse_y2"
      ],
      "オレたちは、いっしょにしあわせな人生をおくる運命にあるんだ。": [
            "fall16_Sebastian_spouse_y2_sv1"
      ],
      "よう、フェスティバルを楽しんでるか？品評会では応援してるぞ！": [
            "fall16_Sam_spouse_y2"
      ],
      "あのな…ルーレットをやるなら… 緑色に賭けた方がいいぜ！": [
            "fall16_Sam_spouse_y2_sv1"
      ],
      "まだ食べてないのか？ほら、たくさんあるぞ！": [
            "fall16_Alex_spouse_y2"
      ],
      "オレはもう3個も食べちまったよ…うーん… このソースがいいんだ…": [
            "fall16_Alex_spouse_y2_sv1"
      ],
      "やあ、ハニー。品評会でいい結果が出るといいですね。あなたなら優勝間違いなしだと思っていますよ。": [
            "fall16_Harvey_spouse_y2"
      ],
      "勝利！5匹釣りあげてスコアは「216」… 自己ベストを更新したよ！": [
            "fall16_Elliott_spouse_y2"
      ],
      "さあ、このスタートークンを使って、きみにふさわしい賞品を選ばなくてはならないね…": [
            "fall16_Elliott_spouse_y2_sv1"
      ],
      "なにか食べに行きたいから、動物たちを見ててくれないか？": [
            "fall16_Shane_spouse_y2"
      ],
      "この剣はとてもエレガントだわ。いつか買えるようにお金をためなくちゃ！": [
            "fall16_Abigail_y2"
      ],
      "木を上手に扱いたいのなら、木の気持ちになって考えなければいけないの…": [
            "fall16_Robin_y2"
      ],
      "羊には優れた記憶力がある… 仲間同士だけではなく人間とも良好な関係を築くことができる…": [
            "fall16_Demetrius_y2"
      ],
      "私たち人間が強い絆で結ばれているのと同じように、彼らは友情を育んでいるんだ！": [
            "fall16_Demetrius_y2_sv1"
      ],
      "やりたいことがたくさんあるわ！何から始めようかしら。": [
            "fall16_Maru_y2"
      ],
      "あの女性に未来を占ってもらったんだ。オレはどう生きたらいいんだろうな…": [
            "fall16_Sebastian_y2"
      ],
      "動物は小さな人間のようなものだ… 知恵や感情を持っている。": [
            "fall16_Linus_y2"
      ],
      "今年の品評会では必ず優勝しますよ！": [
            "fall16_Pierre_y2"
      ],
      "品評会に出す作物のなかには、私の温室で採れたものもあるのよ。私たちが一年をかけて大切に育ててきたものなの！": [
            "fall16_Caroline_y2"
      ],
      "ちからだめしで100回勝つごとにバーベキューサンドを食べてるんだ。": [
            "fall16_Alex_y2"
      ],
      "%ジョージは今にも眠ってしまいそうだ。": [
            "fall16_George_y2"
      ],
      "うふふ…ピエロの人形集めを始めようかしら…": [
            "fall16_Evelyn_y2"
      ],
      "やあ、 @！ついに「スターデューバレーまつり」の当日だ。お客さんも増えてきたようだね。": [
            "fall16_Lewis_y2"
      ],
      "今年も品評会のための展示台を用意したよ。準備ができたら審査を始めるから、私に声をかけてくれ。": [
            "fall16_Lewis_y2_sv1"
      ],
      "おれの仕事に興味を持ってくれる人がいるのは励みになるよ。世界の役に立つ仕事をしている気分になるんだ。": [
            "fall16_Clint_y2"
      ],
      "先週仕上げたばかりのものもある。ゆっくり見ていってくれ。オレはこの仕事を誇りに思うよ！": [
            "fall16_Clint_y2_sv1"
      ],
      "ふぅ… 一日中立ってばかりだったから、ゆっくり休んでいるところよ。": [
            "fall16_Penny_y2"
      ],
      "人生は楽しまなくちゃだめだよ、若いの！": [
            "fall16_Pam_y2"
      ],
      "サンディと私が小さかった頃、2人で家出してサーカスに入ろうって言ってたの。": [
            "fall16_Emily_y2"
      ],
      "そんなこと出来るわけないけど、あれこれ想像するのが楽しかったわ。": [
            "fall16_Emily_y2_sv1"
      ],
      "今年の秋はダイエットしようと思ってるのに… このジューシーなハンバーガーには負けそうだわ！": [
            "fall16_Haley_y2"
      ],
      "やだ、またゴミのポイ捨てだわ。": [
            "fall16_Jodi_y2"
      ],
      "マナーが悪い観光客って毎年いるのよね…": [
            "fall16_Jodi_y2_sv1"
      ],
      "ふふ… 息子はこういうのが得意なんだ。オレから受け継いだのかもな。": [
            "fall16_Kent_y2"
      ],
      "新しい武器が欲しいんだ。クリントと交渉してみるか…": [
            "fall16_Marlon_y2"
      ],
      "くっ…ルーレットの賭けに全部負けちまった…": [
            "fall16_Sam_y2"
      ],
      "緑にしときゃよかった…": [
            "fall16_Sam_y2_sv1"
      ],
      "ロビンと私はいいコンビだって思わない？": [
            "fall16_Leah_y2"
      ],
      "好物をあげたから動物たちは満足してるよ。": [
            "fall16_Shane_y2"
      ],
      "なでても噛んだりしないさ。": [
            "fall16_Shane_y2_sv1"
      ],
      "今年はうちの動物たちが元気いっぱいだったの！審査では生産品の質の高さを評価してもらえると思うわ。": [
            "fall16_Marnie_y2"
      ],
      "@、あなたの展示品はどう？努力の成果を披露する最高の舞台よ。": [
            "fall16_Marnie_y2_sv1"
      ],
      "においは気にしないでくれ…釣りゲームのブースから出てきたばかりなんだ。": [
            "fall16_Elliott_y2"
      ],
      "さて、このスタートークンをどう使おうかな…": [
            "fall16_Elliott_y2_sv1"
      ],
      "4つのグリルで同時に料理するのは大変な仕事さ！今日はお腹を空かせたお客さんがたくさんいるからね。": [
            "fall16_Gus_y2"
      ],
      "どのパテにも特製のピリ辛ソースがちょっとだけ入ってるんだ。（ウィンク）": [
            "fall16_Gus_y2_sv1"
      ],
      "この人間の集まりに興味があったんだ…": [
            "fall16_Dwarf_y2"
      ],
      "誰にも言わないでくれ。このまま隠れていたいんだ…": [
            "fall16_Dwarf_y2_sv1"
      ],
      "霧の向こうの未来を覗きたいのなら、吾輩の同朋のウェルウィックに見てもらうといい。": [
            "fall16_Wizard_y2"
      ],
      "彼女には類まれな才能がある…": [
            "fall16_Wizard_y2_sv1"
      ],
      "木の側にいるあの若者は、自分が創作した書物に興味をもっていたようだが、私の力をもってしても心の奥底にある秘密を探ることはできないのだ…": [
            "fall16_Wizard_y2_sv2"
      ],
      "磨き上げられた職人技に驚いています。才能のある方たちばかりです！": [
            "fall16_Harvey_y2"
      ],
      "スターデューバレーの人たちのつながりは、ほかのどこにもないものだわ…": [
            "fall16_Sandy_y2"
      ],
      "モー！モー！": [
            "fall16_Jas_y2"
      ],
      "牛の赤ちゃんとお話ししたいの。": [
            "fall16_Jas_y2_sv1"
      ],
      "お父さん！もう一回的あてゲームをやってもいい？お願い！": [
            "fall16_Vincent_y2"
      ],
      "品評会に間に合うようにイリジウム品質の魚を何匹か釣ってきたんだ！": [
            "fall16_Willy_y2"
      ],
      "品評会が終わったら次は釣りゲームのテントに行くつもりさ。": [
            "fall16_Willy_y2_sv1"
      ],
      "この鳥たちと友だちになったんだ！": [
            "fall16_Leo_y2"
      ]
}