{
      "Ruhluk Arefesi": [
            "fall27_name"
      ],
      "Devamında ne var söylemen lazım, gidemem ben... Örümcekler vardır kesin...": [
            "fall27_Abigail_spouse"
      ],
      "Birazcık fazla kabak birası içmiş olabilirim...": [
            "fall27_Leah_spouse"
      ],
      "Kafam karıştı... Sen devam et. Ben bununla ilgileneceğim.": [
            "fall27_Maru_spouse"
      ],
      "Ah... Şu buharlar... Hım... Bu gece çok şıksın.": [
            "fall27_Penny_spouse"
      ],
      "Kolayca korkabiliyorum... Ben burada bekleyeceğim ya.": [
            "fall27_Haley_spouse"
      ],
      "Çiflikte bunlardan bir tane olsa ilginç olurdu.": [
            "fall27_Sebastian_spouse"
      ],
      "Selam. Ben de ne zaman geleceğini merak ediyordum!": [
            "fall27_Sam_spouse"
      ],
      "Merhaba... Beni burada bulmanı umuyordum...": [
            "fall27_Harvey_spouse"
      ],
      "Hım... Fazladan birkaç dilim kabak tatlısı yemiş olabilirim.": [
            "fall27_Elliott_spouse"
      ],
      "Devam edemem... Örümcekler...": [
            "fall27_Abigail"
      ],
      "Eh, kış neredeyse geldi. Taş ve odun depolamak için harika bir zaman.": [
            "fall27_Robin"
      ],
      "Saatlerdir Maru'yu görmedim... Umarım iyidir.": [
            "fall27_Demetrius"
      ],
      "Sanırım buradan daha önce geçmiştim... Hayır, bir dakika...": [
            "fall27_Maru"
      ],
      "Of, kayboldum...": [
            "fall27_Maru_sv1"
      ],
      "Bu iskeletler nasıl yürüyor hiç bilemiyorum... Ürkütücü.": [
            "fall27_Sebastian"
      ],
      "Aynı zamanda havalı.": [
            "fall27_Sebastian_sv1"
      ],
      "??": [
            "fall27_Pierre"
      ],
      "Kolayca korkabiliyorum. Perili labirentten gençler geçsin.": [
            "fall27_Caroline"
      ],
      "Güzel gösteri, eski dostum.": [
            "fall27_Linus"
      ],
      "Şurada garip bir şey var da oraya nasıl gideceğim?": [
            "fall27_Alex"
      ],
      "Burada bir yerde gizli bir geçit olmalı.": [
            "fall27_Alex_sv1"
      ],
      "Hım... Tütsülenmiş hindi butu mu? Bu şölen o kadar da kötü değilmiş.": [
            "fall27_George"
      ],
      "Gus keşke bir de vejetaryen opsiyonu sunsaymış. Belki biraz kabak şiş...": [
            "fall27_Evelyn"
      ],
      "İyi akşamlar @. Perili labirentten geçtin mi? Bayağı ürkütücü.": [
            "fall27_Lewis"
      ],
      "Şuradaki garip adam yaşadığı o kuleyi tek başına yapmıştı. İnşaata kimseyi yaklaştırmazdı.": [
            "fall27_Lewis_sv1"
      ],
      "İridyum alaşımlı gürzlerimden birisi bunların icabından kolayca gelirdi...": [
            "fall27_Clint"
      ],
      "Kabak fenerlerimi sevdin mi? Kendim oydum.": [
            "fall27_Emily"
      ],
      "Şu kazandan gelen buhar... başımı döndürüyor ama uzak duramıyorum...": [
            "fall27_Penny"
      ],
      "Beleş yemek olan her etkinliğe gelirim! Ancak, beni perili labirentte göremezsin.": [
            "fall27_Pam"
      ],
      "Oy oy! Çok korktum.": [
            "fall27_Haley"
      ],
      "Perili labirente girmesine izin vermediğim için Vincent bana küstü... Daha çok küçük!": [
            "fall27_Jodi"
      ],
      "Selam @. Güzel bir akşam. Sence de öyle değil mi?": [
            "fall27_Kent"
      ],
      "Bu garip... Bildiğin çıkmaz yol.": [
            "fall27_Sam"
      ],
      "Labirentten geçerken önümde bir ölü olduğuna yemin edebilirim. Nereye gitti?": [
            "fall27_Sam_sv1"
      ],
      "Ihım, selamlar. Kusura bakma... Ağzım böğürtlen dolu.": [
            "fall27_Leah"
      ],
      "Selam @. Verimli bir güz geçirdin mi?": [
            "fall27_Marnie"
      ],
      "Havalar soğumaya başladı... Ekinler daha fazla dayanmaz.": [
            "fall27_Marnie_sv1"
      ],
      "Ah, merhaba @. Hava biraz soğuk, değil mi?": [
            "fall27_Elliott"
      ],
      "Bal kabağı ile bir şeyler pişirmek çok eğlenceli. Çok ilginç bir sebze.": [
            "fall27_Gus"
      ],
      "Yağmur mu yağıyor? *şaşırır*": [
            "fall27_Dwarf"
      ],
      "Yağmur... Bizim için neredeyse efsanevi bir şeydir. Kimimiz hayatları boyunca yağmuru göremeden ölür.": [
            "fall27_Dwarf_sv1"
      ],
      "Yerel halkın dünyevi zevkleri umurumda değil. Ancak, elementaller insanları yakından görmek istiyor.": [
            "fall27_Wizard"
      ],
      "Onlar için bu labirenti kurdum.": [
            "fall27_Wizard_sv1"
      ],
      "Ah! Beni buldun...": [
            "fall27_Harvey"
      ],
      "Açık konuşacağım, burada çok korktuğum için saklanıyordum. Kimseye söyleme.": [
            "fall27_Harvey_sv1"
      ],
      "Neden daha fazla kabak birası yok?": [
            "fall27_Shane"
      ],
      "Bizim orada yağmur yağdığını duydum. Sen bu yüzden mi buraya geldin?": [
            "fall27_Sandy",
            "fall27_Sandy_y2"
      ],
      "Aslında, yağmuru özlüyorum...": [
            "fall27_Sandy_sv1",
            "fall27_Sandy_y2_sv1"
      ],
      "Ama Marnie teyze! Labirente girmek istiyorum! Korkmuyorum ben!": [
            "fall27_Jas"
      ],
      "Annem beni labirente sokmuyor. *hıçkırır*": [
            "fall27_Vincent"
      ],
      "Kafese fazla yaklaşma.": [
            "fall27_Marlon"
      ],
      "%Leo, asla kapamadığı gözleriyle etrafı izliyor. Dikkatini çekmek için yapabileceğin hiçbir şey yok.": [
            "fall27_Leo"
      ],
      "BO 113 5000 1 O 746 750 5 BL 746 2000 1 BO 47 350 -1 F 2870 4000 -1": [
            "fall27_shop_y2"
      ],
      "Bu canavarlarla daha önce savaştın mı?": [
            "fall27_Abigail_spouse_y2"
      ],
      "Örümceklerle... Bile mi?": [
            "fall27_Abigail_spouse_y2_sv1"
      ],
      "Muhtemelen labirente girmeden önce fazla bal kabağı birası içtim.": [
            "fall27_Leah_spouse_y2"
      ],
      "Sen önden git, ben seni yakalarım.": [
            "fall27_Leah_spouse_y2_sv1"
      ],
      "Bir tabak kapıp ailene katıl!": [
            "fall27_Maru_spouse_y2"
      ],
      "*oflar* Labirentte kayboldum...": [
            "fall27_Penny_spouse_y2"
      ],
      "Ben burada kapana kısılmışken herkes evine dönecek diye çok korktum!2": [
            "fall27_Penny_spouse_y2_sv1"
      ],
      "*kıkırdar* Burada yolunu bulabileceğini biliyordum.": [
            "fall27_Emily_spouse_y2"
      ],
      "Hah! Bunların hiçbiri gerçek değil.": [
            "fall27_Haley_spouse_y2"
      ],
      "... Değil mi @? Gerçek değil... Değil mi?2": [
            "fall27_Haley_spouse_y2_sv1"
      ],
      "Vay be, ürkütücü elleri geçebilmişsin.": [
            "fall27_Alex_spouse_y2"
      ],
      "Sanırım birinin yardım çağırdığını duydum.": [
            "fall27_Alex_spouse_y2_sv1"
      ],
      "Hey, bana bir... El atar mısın? Hehehe...": [
            "fall27_Sebastian_spouse_y2"
      ],
      "Bu mezar taşları, çiftlikte güzel dururdu. Sence de öyle olmaz mıydı?": [
            "fall27_Sebastian_spouse_y2_sv1"
      ],
      "Kardeşimle oldukça ilerledik ama burada takıldık.": [
            "fall27_Sam_spouse_y2"
      ],
      "Sen önden git... O hazineleri bizim için bul!": [
            "fall27_Sam_spouse_y2_sv1"
      ],
      "Seni ne zaman göreceğimi merak ediyordum.": [
            "fall27_Harvey_spouse_y2"
      ],
      "Boş ver beni. Sadece ufak bir mola veriyorum.": [
            "fall27_Harvey_spouse_y2_sv1"
      ],
      "Bunların serbest kalması ihtimali beni ürpertiyor...%noturn": [
            "fall27_Elliott_spouse_y2"
      ],
      "Korkma sevgilim! O lanetli yaratığı, sana daha dokunamadan yok ederdim.": [
            "fall27_Elliott_spouse_y2_sv1"
      ],
      "Marnie'yi, Jas'i labirente götürmeye ikna ettim. Bence artık yeterince büyüdü.": [
            "fall27_Shane_spouse_y2"
      ],
      "Ama çok yavaş ilerliyoruz. Bizsiz devam et!": [
            "fall27_Shane_spouse_y2_sv1"
      ],
      "Bizim evdeki süslemeleri gördün mü? Sevmedim...": [
            "fall27_Abigail_y2"
      ],
      "Ortalığın sakinlemesini bekleyenlerden misin? Kış geliyor.": [
            "fall27_Robin_y2"
      ],
      "Biliyor muydun... Antropolojik Fizyoloji Dergisi'nde yapılan bir araştırma; müziğin ritmi, temposu ve tonunun kortizol seviyeleri üzerinde ölçülebilir bir etkisi olduğunu bulmuş.": [
            "fall27_Demetrius_y2"
      ],
      "Şey... Böğürtlenli turta ile vanilyalı dondurma var mı?": [
            "fall27_Demetrius_y2_sv1"
      ],
      "Bunu yer yemez labirente dalacağım!": [
            "fall27_Maru_y2"
      ],
      "Burası benim bölgem.": [
            "fall27_Sebastian_y2"
      ],
      "Aa, bu çiftçi @! Bugün seçkin bazı ürünlerim var. Gel de göz at!": [
            "fall27_Pierre_y2"
      ],
      "Eşime bir tabak yemek hazırlamalıyım. Bütün akşam çalıştı.": [
            "fall27_Caroline_y2"
      ],
      "Haha! İşte bir başka harika eser eski dostum.": [
            "fall27_Linus_y2"
      ],
      "Sanırım bir kız çığlığı duydum... Yardımıma ihtiyacı var!": [
            "fall27_Alex_y2"
      ],
      "Bu lanet sandalyede olmasaydım herkesle birlikte labirentte koşuşturuyor olurdum!": [
            "fall27_George_y2"
      ],
      "Canım, kabak böreğini uzatır mısın?": [
            "fall27_Evelyn_y2"
      ],
      "İyi akşamlar @. Ormanda yaşayan münzevimiz, gizlice inşa ettiği bu labirenti bir kez daha bize bahşetti.": [
            "fall27_Lewis_y2"
      ],
      "Bu seferki daha büyükmüş. Gireceksen sana bol şans diliyorum...": [
            "fall27_Lewis_y2_sv1"
      ],
      "Labirenti çoktan aştım... Şimdi bal kabağı birası içme zamanı!": [
            "fall27_Clint_y2"
      ],
      "...Arkamdaki örümcek istilasını görmezden gelmek için elimden geleni yapıyorum.": [
            "fall27_Clint_y2_sv1"
      ],
      "Oo. Gizli geçidi sen de bulmuşsun!": [
            "fall27_Emily_y2"
      ],
      "Bir süreliğine labirentteydim fakat sonra acıktım.": [
            "fall27_Penny_y2"
      ],
      "Annem tek başına oldukça eğleniyor gibi görünüyor.": [
            "fall27_Penny_y2_sv1"
      ],
      "Bu tarafa başka bir şişe daha bal kabağı birası gönder!.. *hıçkırır*": [
            "fall27_Pam_y2"
      ],
      "Kardeşimi gördün mü?": [
            "fall27_Haley_y2"
      ],
      "Emily! Beni duyabiliyor musun?": [
            "fall27_Haley_y2_sv1"
      ],
      "Sam, Vincent'ı labirente götürdü. Umarım iyilerdir...": [
            "fall27_Jodi_y2"
      ],
      "Bunlar pek de zor görünmüyor.": [
            "fall27_Kent_y2"
      ],
      "Ben Sam miyim? Heh, heh, heh...1": [
            "fall27_Sam_y2"
      ],
      "Bu taraftan mı? Belki de bu taraftan?": [
            "fall27_Leah_y2"
      ],
      "Umarım Jas iyidir.": [
            "fall27_Marnie_y2"
      ],
      "Çiftçilikte başarılı bir yıl geçirdin mi @?": [
            "fall27_Marnie_y2_sv1"
      ],
      "Ah, zavallı varlık... Acaba hangi kokmuş mağarada gizleniyorsun?%noturn": [
            "fall27_Elliott_y2"
      ],
      "Bazen ilham perisini uyandırmak için derinlere bakmak gerekebilir...": [
            "fall27_Elliott_y2_sv1"
      ],
      "Bal kabağı oyma konusunda yetenekliyim. Genellikle kasabadaki herkes için Cadılar Bayramı fenerlerini ben yaparım.": [
            "fall27_Gus_y2"
      ],
      "Karşılığında tek istediğim çekirdekleri saklamak... Biraz tarçın ve şeker serpip yediğinde harika bir atıştırmalık oluyorlar!": [
            "fall27_Gus_y2_sv1"
      ],
      "Burası çok garip...": [
            "fall27_Dwarf_y2"
      ],
      "Denemeler devam ediyor... Her büyücünün bir çırağı olmalı...": [
            "fall27_Wizard_y2"
      ],
      "Korkarım ki bu sefer kafam çok karışmış durumda...": [
            "fall27_Harvey_y2"
      ],
      "Bana yakın dur Jas. Koşma!%noturn": [
            "fall27_Shane_y2"
      ],
      "Hadi bu taraftan gidelim!%noturn": [
            "fall27_Jas_y2"
      ],
      "Dikkatli ol oğlum... O labirentte kötü bir şey var...": [
            "fall27_Willy_y2_male_farmer"
      ],
      "Dikkatli ol kızım... O labirentte kötü bir şey var...": [
            "fall27_Willy_y2_female_farmer"
      ],
      "Labirenti geçtik mi? Ödülüm nerede?": [
            "fall27_Vincent_y2"
      ],
      "Bu sene daha fazla canavar yakaladım. Kafeslerden uzakta kalmaya dikkat et.": [
            "fall27_Marlon_y2"
      ],
      "Labirent içinde başka bir labirent... Başım dönüyor...": [
            "fall27_Leo_y2"
      ],
      "Burada ne yapıyorsun?": [
            "fall27_Krobus_y2"
      ]
}