{
    "Ehi! Oh, benone, hai portato la torta!...": "Town_6184644_220_Haley_event1",
    "Sembra davvero gustosa. Grazie, @.": "Town_6184644_220_Haley_event2",
    "C'è stata una bella partecipazione, eh?": "Town_6184644_220_Haley_event3",
    "Ehm... Haley? Quando ci fermiamo? Le... mie gambe... *pant* *pant*": "Town_6184644_220_Marnie_event1",
    "Oooops! Mi sono scordata di suonare il fischietto.": "Town_6184644_220_Haley_event4",
    "D'accordo! Tutti dovrebbero trovarsi su un quadrato numerato.": "Town_6184644_220_Haley_event5",
    "Io sì!": "Town_6184644_220_Emily_textAboveHeadEvent1",
    "Già": "Town_6184644_220_Marnie_textAboveHeadEvent2",
    "Proprio così": "Town_6184644_220_Pam_textAboveHeadEvent1",
    "I numeri determinano quale torta vincerete!": "Town_6184644_220_Haley_event6",
    "Ok, vediamo chi si prende cosa...": "Town_6184644_220_Haley_event6_sv1",
    "Dunque, vediamo...": "Town_6184644_220_Haley_event7",
    "Caroline, che numero hai? Ok... hai vinto...": "Town_6184644_220_Haley_event7_sv1",
    "Il panpepato di carote di grotta del sindaco Lewis... con fibre extra!": "Town_6184644_220_Haley_event7_sv2",
    "Che bello": "Town_6184644_220_Caroline_textAboveHeadEvent1",
    "Emily, per te ci sono...": "Town_6184644_220_Haley_event8",
    "I tortini di birra scura al cioccolato di Pam, con crema al bourbon invecchiato.": "Town_6184644_220_Haley_event8_sv1",
    "Buoni!": "Town_6184644_220_Gus_textAboveHeadEvent1",
    "Preparati a vedere le stelle, giovane.": "Town_6184644_220_Pam_event2",
    "Poi... Jas, tu hai vinto...": "Town_6184644_220_Haley_event9",
    "La torta di rafani selvatici di Clint.": "Town_6184644_220_Haley_event9_sv1",
    "È una vecchia ricetta di famiglia. L'ho fatta lievitare direttamente nel forno della forgia.": "Town_6184644_220_Clint_event1",
    "Oh, ehm... Forse il fondo si è un po' bruciacchiato, quindi... ehm... può darsi che dovrai levare uno strato di crosta carbonizzata. Però il resto è del tutto commestibile.": "Town_6184644_220_Clint_event1_sv1",
    "Ehm, va bene... Il prossimo è Vincent. Abbiamo...": "Town_6184644_220_Haley_event10",
    "Il triplo tronco candito con crema e sciroppo alla fragola di Robin!": "Town_6184644_220_Haley_event10_sv1",
    "Oh no...": "Town_6184644_220_Jodi_textAboveHeadEvent1",
    "La prossima è Jodi. Ti porterai a casa...": "Town_6184644_220_Haley_event11",
    "La torta biologica di velluto rosso di Emily... colorata con le barbabietole!": "Town_6184644_220_Haley_event11_sv1",
    "Gnam!": "Town_6184644_220_Jodi_textAboveHeadEvent2",
    "...e ultima, ma non per importanza: Pam! Sei la fortunata vincitrice della torta al cioccolato deluxe di mio marito.": "Town_6184644_220_Haley_event12_male_farmer",
    "...e ultima, ma non per importanza: Pam! Sei la fortunata vincitrice della torta al cioccolato deluxe di mia moglie.": "Town_6184644_220_Haley_event12_female_farmer",
    "Grazie, giovane": "Town_6184644_220_Pam_textAboveHeadEvent3",
    "Grazie a tutti per aver partecipato. Abbiamo raccolto più di 5.000o!": "Town_6184644_220_Haley_event13",
    "A proposito, a che ti servono quei soldi? Ti compri una borsetta nuova?": "Town_6184644_220_George_event1",
    "In realtà... sono per Penny.": "Town_6184644_220_Haley_event14",
    "Penny, l'altro giorno ti ho sentita mentre parlavi con Jas e Vincent dei loro libri di scuola. Sembrava che ti servisse una mano...": "Town_6184644_220_Haley_event15",
    "Libri nuovi!": "Town_6184644_220_Penny_textAboveHeadEvent1",
    "Avete sentito, bambini? Presto avrete dei libri nuovi di zecca!": "Town_6184644_220_Penny_event2",
    "Non so cosa dire... Grazie di cuore.": "Town_6184644_220_Penny_event3",
    "...a tutt'e due!": "Town_6184644_220_Penny_event3_sv1",
    "Ehi, Lewis... visto che stiamo finanziando l'istruzione senza toccare le casse del paese, ci abbasserai l'imposta sugli affari, giusto?": "Town_6184644_220_Robin_event1",
    "È stato un successone! Grazie per avermi dato una mano, amore.": "Town_6184644_220_Haley_endDialogue16"
}