{
    "¡Ah! ¡Hola, @! Adelante, adelante.": "LeahHouse_50_Leah_Leah_event1",
    "Estoy trabajando en esta escultura.": "LeahHouse_50_Leah_Leah_event2",
    "Ven aquí. Mira esto.": "LeahHouse_50_Leah_Leah_event3",
    "¿Lo ves? Estoy revelando la esencia de la madera.": "LeahHouse_50_Leah_Leah_event4",
    "Una vez vas más allá de las capas exteriores, empieza a aparecer su verdadera naturaleza...": "LeahHouse_50_Leah_Leah_event5",
    "Vine al valle por primera vez de niña, de vacaciones con mis padres.": "LeahHouse_50_Leah_Leah_event6",
    "Supe que algún día volvería... ¡Este lugar tiene un potencial artístico enorme!": "LeahHouse_50_Leah_Leah_event6_sv1",
    "Aunque, bueno... No es fácil pagar las facturas siendo artista.": "LeahHouse_50_Leah_Leah_event7",
    "Hmmm... Interesante. Supongo que eso podría empezar a convertir Pueblo Pelícano en un destino artístico...": "LeahHouse_50_Leah_Leah_event8",
    "Pero... ¿Y si a nadie le gustan mis esculturas? Me rompería el corazón.": "LeahHouse_50_Leah_Leah_event9",
    "Tengo que meditarlo bien...": "LeahHouse_50_Leah_Leah_event10",
    "Bueno, gracias por pasarte, @.": "LeahHouse_50_Leah_Leah_event11",
    "¿Una exposición de arte para todo el pueblo? Es una idea atrevida, @.": "LeahHouse_50_Leah_Leah_endDialogue12"
}