{
	"Changes": [
	
		{
            "Action": "EditData",
            "Target": "{{Platonymous.ScaleUp/Assets}}",
            "Entries": {
                "{{ModId}}.Bouncer": {
                    "Asset": "Portraits/Bouncer",
                    "Scale": 4
                },
				"{{ModId}}.Grandpa": {
                    "Asset": "Portraits/Grandpa",
                    "Scale": 4
                },
				"{{ModId}}.Henchman": {
                    "Asset": "Portraits/Henchman",
                    "Scale": 4
                },
				"{{ModId}}.Governor": {
                    "Asset": "Portraits/Governor",
                    "Scale": 4
                },	
				"{{ModId}}.AnsweringMachine": {
                    "Asset": "Portraits/AnsweringMachine",
                    "Scale": 4
                },						
			}
		},	
		{
            "LogName": "Load Miscellaneous Characters",
            "Action": "Load",
			"Priority": "High",
            "Target": "Portraits/Bouncer, Portraits/Grandpa, Portraits/Governor, Portraits/Henchman, Portraits/AnsweringMachine",
            "FromFile": "assets/{{Target}}.png",
            "When":
            {
                "HasFile:{{FromFile}}": true,
            }        
		},	
		{
            "LogName": "Edit Miscellaneous Characters",
            "Action": "EditImage",
            "Target": "Portraits/Bouncer, Portraits/Grandpa",
            "FromFile": "assets/{{Target}}.png",
            "When":
            {
                "HasFile:{{FromFile}}": true,
            }        
		},			

	]
}
