{
    "오! @.": "Forest_14_sunny_Haley_event1",
    "지금 자연광이 너무 좋아... 나와서 사진 좀 찍어야겠다 싶었어.": "Forest_14_sunny_Haley_event2",
    "요즘 야외활동을 더 많이 하려는 중이야...": "Forest_14_sunny_Haley_event3",
    "어떤지 알고 싶어, 농부로 지내면 어떤지. 내가 생각해보지 못한 삶의 방식이라서.": "Forest_14_sunny_Haley_event3_sv1",
    "뭐, 적어도 지금까지는...": "Forest_14_sunny_Haley_event3_sv2",
    "헤, 저 소들 너무 귀엽다...": "Forest_14_sunny_Haley_event4",
    "아, 나 생각이 있어!": "Forest_14_sunny_Haley_event5",
    "소랑 같이 사진 찍자! 어떻게 다가가야 하는지 보여줘.": "Forest_14_sunny_Haley_event6",
    "사진은 그냥 타이머로 찍히게 할게.": "Forest_14_sunny_Haley_event6_sv1",
    "...에...": "Forest_14_sunny_Haley_event7",
    "*히히*0": "Forest_14_sunny_Haley_event8",
    "재밌었어, @! ...그리고 사진들 너무 웃기다!0": "Forest_14_sunny_Haley_event8_sv1",
    "이제 집에 가서 샤워해야지...0": "Forest_14_sunny_Haley_event9",
    "이렇게 지저분해본 적도 없네.": "Forest_14_sunny_Haley_endDialogue10"
}