{
      "Пир Зимней звезды": [
            "winter25_name"
      ],
      "Интересно, эти леденцы можно лизнуть?": [
            "winter25_Abigail_spouse"
      ],
      "Я благодарна за нашу простую фермерскую жизнь.": [
            "winter25_Leah_spouse"
      ],
      "Привет, @. Я готова пойти домой, когда захочешь.": [
            "winter25_Maru_spouse"
      ],
      "Я благодарна за то, что встретила тебя...": [
            "winter25_Penny_spouse"
      ],
      "Я? А, я благодарна за... Давай я тебе дома покажу, за что?": [
            "winter25_Haley_spouse"
      ],
      "Привет, @. Я тут, как видишь, выполняю семейные обязанности...": [
            "winter25_Sebastian_spouse"
      ],
      "*зевает*... Я пришел только ради печенек и подарков.": [
            "winter25_Sam_spouse"
      ],
      "За что я благодарен? Покажу, когда вернемся домой...": [
            "winter25_Alex_spouse"
      ],
      "Что-то мне немного не по себе... Хорошо, что воздух такой свежий...": [
            "winter25_Harvey_spouse"
      ],
      "Мне ничего от тебя не нужно, ведь я уже получил от тебя самый лучший подарок...": [
            "winter25_Elliott_spouse"
      ],
      "Горячая объедаловка посреди холодного зимнего дня — что может быть лучше?": [
            "winter25_Abigail"
      ],
      "Приветик, @. Если нужна компания, присоединяйся к нашему семейному столу.": [
            "winter25_Robin"
      ],
      "Я и в этом году, наверное, получу набор инструментов в подарок... Эх.": [
            "winter25_Demetrius"
      ],
      "Привет, @.": [
            "winter25_Maru"
      ],
      "Я знавал людей, которые верят в духов и волшебство... А что я? Я еще не видел ничего такого, чего бы не смогла объяснить наука.": [
            "winter25_Shane"
      ],
      "Иногда проводить время с семьей так утомительно.": [
            "winter25_Sebastian"
      ],
      "Прибыль в последнее время подскочила до небес... Все благодаря Пиру Зимней звезды!": [
            "winter25_Pierre"
      ],
      "Ох, как же выгодны праздники. Может, придумать еще парочку новых?": [
            "winter25_Pierre_sv1"
      ],
      "У-ух-х-х... Слишком много я выпила гоголя-моголя.": [
            "winter25_Caroline"
      ],
      "Я бы присоединился к остальным, но не думаю, что меня там ждут...": [
            "winter25_Linus"
      ],
      "Ой, привет.": [
            "winter25_Alex"
      ],
      "Целый пир ради какой-то дурацкой звезды? Что за вздор!": [
            "winter25_George"
      ],
      "Вот это да! Тебе разве не холодно, деточка? Такой мороз на дворе!": [
            "winter25_Evelyn"
      ],
      "Сегодня мы все благодарны за удачу, которую принес этот год. Забудь о своих тревогах и расслабься!": [
            "winter25_Lewis"
      ],
      "Эх... Все эти счастливые семейки вокруг... А для меня это очередной одинокий год.": [
            "winter25_Clint"
      ],
      "@! А что ты хочешь найти под елочкой?": [
            "winter25_Emily"
      ],
      "Только и мыслей, что о работе, да? Это совсем не весело.": [
            "winter25_Emily__Новую_лейку___response"
      ],
      "У-у-у... Звучит здорово. Не забудь и со мной поделиться.": [
            "winter25_Emily__Графин_пряной_медовухи___response"
      ],
      "Понятно. Да, это был бы подарок что надо!'": [
            "winter25_Emily__Пару_стильных_ботинок___response"
      ],
      "Какое красивое дерево.": [
            "winter25_Penny"
      ],
      "Пф-ф... Я все еще недовольна, что не выиграла соревнование по подледному лову.": [
            "winter25_Pam"
      ],
      "Надеюсь, под елочкой меня ждет новая камера!": [
            "winter25_Haley"
      ],
      "Не самое удачное время садиться на диету...": [
            "winter25_Jodi"
      ],
      "Добрый день, @. Счастливого Пиршества.": [
            "winter25_Kent"
      ],
      "Я благодарен за гитару и скейтборд. А, ну и за свою семью, наверное.": [
            "winter25_Sam"
      ],
      "Гас тут рассказывал мне про свои шедевральные леденцы. *Зевает*": [
            "winter25_Leah"
      ],
      "Кажется, он выпил слишком много моголя с корицей.": [
            "winter25_Leah_sv1"
      ],
      "Добро пожаловать на Пир Зимней звезды!": [
            "winter25_Marnie"
      ],
      "Ах, здравствуй, @. Весьма прохладно, не правда ли?": [
            "winter25_Elliott"
      ],
      "Изготовление леденцов — тонкое искусство. Нужные ингредиенты подбираются очень и очень тщательно. В последнее время их не так-то просто отыскать!": [
            "winter25_Gus"
      ],
      "Для своих лучших леденцов я использую кольцеплоды с Папоротниковых островов. Их ярко-красный цвет просто незаменим... И никакой химии, все от природы!": [
            "winter25_Gus_sv1"
      ],
      "О, ты хочешь узнать тайну моих особых двойных тросточек? Так и быть, но пообещай, что не скажешь никому. *шепотом* Нужна капля ванили в белой карамели, чтобы подчеркнуть вишневый вкус.": [
            "winter25_Gus_sv2"
      ],
      "Мятные леденцы — это, конечно, классика, поэтому я много их наделал.": [
            "winter25_Gus_sv3"
      ],
      "Эй, ты что-то носом клюешь. Ты в порядке?": [
            "winter25_Gus_sv4"
      ],
      "Хочешь услышать легенду о Зимней звезде?": [
            "winter25_Willy"
      ],
      "В зимнем ночном небе есть одна яркая звезда, которую видно только из нашей долины. Никому не известно, почему это так... Но в былые времена люди приходили издалека, чтобы на нее посмотреть.*Они верили, будто тот, кто увидит Зимнюю звезду, станет очень удачлив. Некоторые даже утверждают, что таинственный плод =звездная капля как-то связан с Зимней звездой.": [
            "winter25_Willy__Да__response"
      ],
      "Как хочешь.'": [
            "winter25_Willy__Нет__спасибо__response"
      ],
      "Ах, таинственная Зимняя звезда. Она — одна из причин, по которой я избрал именно эту долину, чтобы провести мое... исследование.": [
            "winter25_Wizard"
      ],
      "Я благодарен за то, что в этому году никому не понадобилась скорая помощь!": [
            "winter25_Harvey"
      ],
      "Я слышала, будто дома сейчас идет дождь. Ты ведь поэтому здесь?": [
            "winter25_Sandy"
      ],
      "На самом деле, я даже немного скучаю по дождю...": [
            "winter25_Sandy_sv1"
      ],
      "О-о-о! Подарки!": [
            "winter25_Jas"
      ],
      "Уже можно открывать подарки?!": [
            "winter25_Vincent"
      ],
      "Эй, добрый день.": [
            "winter25_Marlon"
      ],
      "Линус не очень хочет к вам присоединяться, поэтому я составлю ему компанию.": [
            "winter25_Leo"
      ],
      "У нас тут свой маленький пир... пюре из зимнего корня и рыба в острой ягодной обмазке!": [
            "winter25_Leo_sv1"
      ],
      "Бр-р... Холодно! Хочу обратно под одеялко...": [
            "winter25_Abigail_spouse_y2"
      ],
      "Эллиот снова пьет слишком много сидра...": [
            "winter25_Leah_spouse_y2"
      ],
      "Увидимся у столика, если я смогу найти выход... Есть хочу!": [
            "winter25_Leah_spouse_y2_sv1"
      ],
      "Я благодарна за любящую семью и тебя в своей жизни...": [
            "winter25_Maru_spouse_y2"
      ],
      "Надеюсь, всем нравятся снегодынные ломтики...": [
            "winter25_Penny_spouse_y2"
      ],
      "Когда я начинаю перечислять все хорошие вещи в своей жизни, мне кажется, что я была благословлена Зимней звездой.": [
            "winter25_Haley_spouse_y2"
      ],
      "Когда мы с Хэйли были детьми, мы украшали печеньки на этом фестивале.": [
            "winter25_Emily_spouse_y2"
      ],
      "Нужно как-нибудь повторить. Нельзя, чтобы традиции вымирали.": [
            "winter25_Emily_spouse_y2_sv1"
      ],
      "Эй... Не переживай, не надо мне ничего дарить.": [
            "winter25_Sebastian_spouse_y2"
      ],
      "Я просто рад просыпаться рядом с тобой каждое утро... О чем еще парень может мечтать?": [
            "winter25_Sebastian_spouse_y2_sv1"
      ],
      "Даже весело смотреть на то, как все разворачивают свои подарки... Смотреть на их реакции.": [
            "winter25_Sam_spouse_y2"
      ],
      "О да, я и тебе кое-что приготовил. Я, эм... покажу, когда вернемся на ферму!0": [
            "winter25_Sam_spouse_y2_sv1"
      ],
      "Скажи, если замерзнешь. Куртку дам.": [
            "winter25_Alex_spouse_y2"
      ],
      "Я за многое благодарен: за мою клинику, хорошее здоровье пациентов...": [
            "winter25_Harvey_spouse_y2"
      ],
      "Но больше всего я благодарен за нашу с тобой совместную жизнь...": [
            "winter25_Harvey_spouse_y2_sv1"
      ],
      "Дорогая моя вторая половинка, мне в этот день ничего не нужно... Ты — самый лучший подарок, о каком вообще можно мечтать.": [
            "winter25_Elliott_spouse_y2"
      ],
      "За что я благодарен?": [
            "winter25_Shane_spouse_y2"
      ],
      "....Эм...": [
            "winter25_Shane_spouse_y2_sv1"
      ],
      "Благодарен за то... что с твоей помощью выбрался из грязи. И с тобой я понял, что я еще хочу жить.": [
            "winter25_Shane_spouse_y2_sv2"
      ],
      "Интересно, какой подарок мой...": [
            "winter25_Abigail_y2"
      ],
      "Надеюсь, это большая коробка!": [
            "winter25_Abigail_y2_sv1"
      ],
      "Что ж... Муж в этом году подарил мне новую электропилу...": [
            "winter25_Robin_y2"
      ],
      "Наврное, забыл, что подарил мне такую же два года назад!": [
            "winter25_Robin_y2_sv1"
      ],
      "Хм-м... У этого зеленого желе мятный вкус.": [
            "winter25_Demetrius_y2"
      ],
      "Хотел бы я знать, как мятный вкус стал ассоциироваться с Пиром Зимней звезды... Мята вообще растет зимой?": [
            "winter25_Demetrius_y2_sv1"
      ],
      "Сегодня довольно холодно. Хорошо, что все утеплились.": [
            "winter25_Maru_y2"
      ],
      "Плюс холодной зимы в том, что можно положить замороженную пиццу под елку.": [
            "winter25_Shane_y2"
      ],
      "Кому-то крупно повезет...": [
            "winter25_Shane_y2_sv1"
      ],
      "Думаю, приятно, когда вся семья собирается хоть раз в году.": [
            "winter25_Sebastian_y2"
      ],
      "Хочешь купить подарок в последнюю минуту? Положись на меня! Взгляни на мои товары.": [
            "winter25_Pierre_y2"
      ],
      "Разве она не красавица?": [
            "winter25_Caroline_y2"
      ],
      "Мы с Марни и Джоди все утро ее наряжали. Славная традиция!": [
            "winter25_Caroline_y2_sv1"
      ],
      "Мэр лично пригласил меня к своему столу. Я просто не мог отказаться!": [
            "winter25_Linus_y2"
      ],
      "Я прямо уверен, что под деревом духов лежит подарок в форме мяча для гридбола с моим именем.": [
            "winter25_Alex_y2"
      ],
      "Я уже провел весь день со своей семьей. Зачем еще толпиться на морозе?": [
            "winter25_George_y2"
      ],
      "Ты всегда можешь присоединиться к нашему столу.": [
            "winter25_Evelyn_y2"
      ],
      "Счастливого Пира Зимней звезды, @.": [
            "winter25_Lewis_y2"
      ],
      "Самое время расслабиться, провести время в хорошей компании и поблагодарить за все, что было.": [
            "winter25_Lewis_y2_sv1"
      ],
      "Вот бы мне подарили новые инструменты для кузницы. А то мои поистаскались со временем.": [
            "winter25_Clint_y2"
      ],
      "Смотрите! Это же «Зимняя звезда»!%noturn": [
            "winter25_Emily_y2"
      ],
      "Ой, ошиблась... Это всего лишь украшение!": [
            "winter25_Emily_y2_sv1"
      ],
      "Привет, @. Какой подарок хочешь получить в этом году?": [
            "winter25_Penny_y2"
      ],
      "А? Никогда о таком не слышала. Кажется, штука не из дешевых.": [
            "winter25_Penny_y2__Иридиевый_подойник__response"
      ],
      "Да, книга может быть очень хорошим подарком!": [
            "winter25_Penny_y2__Интересную_книгу__response"
      ],
      "...Не знаю, серьезно ли ты говоришь, но это довольно полезный подарок!'": [
            "winter25_Penny_y2__Уголек__response"
      ],
      "В этот мороз я выживаю только благодаря глинтвейну!": [
            "winter25_Pam_y2"
      ],
      "Это все так мило... Хотелось бы, чтобы город выглядел так всегда!": [
            "winter25_Haley_y2"
      ],
      "Это место для лишних подарков. В этом году их и правда больше обычного!": [
            "winter25_Jodi_y2"
      ],
      "Я благодарен за то, что мой мальчик счастлив и здоров.": [
            "winter25_Kent_y2"
      ],
      "Да кто вообще дарит корзину из Джоджа?..": [
            "winter25_Sam_y2"
      ],
      "Порой мне тяжело решиться прийти на вечеринку, но потом я всегда рада, что пошла!": [
            "winter25_Leah_y2"
      ],
      "Счастливого Пира, @!": [
            "winter25_Marnie_y2"
      ],
      "*рыг*": [
            "winter25_Elliott_y2"
      ],
      "Ой... Простите. Где мои манеры? Этот сидр со специями сильно газированный.": [
            "winter25_Elliott_y2_sv1"
      ],
      "Ешьте! Ешьте, пока все свежее и горячее.": [
            "winter25_Gus_y2"
      ],
      "Мог бы рассказать, какой новый метод изготовления карамельных тростей я изобрел... Но в этом году не буду!": [
            "winter25_Gus_y2_sv1"
      ],
      "Я человек простой, @... Благодарен за крепкую крышу над головой и банку горячих бобов по утру!": [
            "winter25_Willy_y2"
      ],
      "А, таинственная Зимняя звезда. Одна из причин, по которой я выбрал Долину местом для своего... исследования.": [
            "winter25_Wizard_y2"
      ],
      "Как тебе пирог с пеканом? Мой любимый.": [
            "winter25_Harvey_y2"
      ],
      "Уже можно открывать подарки?": [
            "winter25_Jas_y2"
      ],
      "Мне подарили игрушечного динозавра, которого я так хотел! Видишь!?": [
            "winter25_Vincent_y2"
      ],
      "Он называется, эм... сте-...стего-...стегонозавр! ...Наверное.": [
            "winter25_Vincent_y2_sv1"
      ],
      "Хм-м? О, привет.": [
            "winter25_Marlon_y2"
      ],
      "Обо мне не беспокойся. Веселись.": [
            "winter25_Marlon_y2_sv1"
      ],
      "Я большинство этих блюд даже не знаю... Но тут все такое вкусное!": [
            "winter25_Leo_y2"
      ]
}