{
      "A Holdfény medúzák tánca": [
            "summer28_name"
      ],
      "Üdv. Épp tisztelgek egy ismételten elmúlt nyárnak. Majd találkozunk, ha útnak indítjuk a gyertya-hajót.": [
            "summer28_Leah_spouse"
      ],
      "Olyan ritka és izgalmas dolog...": [
            "summer28_Abigail"
      ],
      "*ásít*... Már aludnom kellene.": [
            "summer28_Robin"
      ],
      "Hé, láttad azt a gyertya-hajót? Én magam készítettem.": [
            "summer28_Robin_sv1"
      ],
      "A 'Holdfény medúza'... micsoda bámulatos faj! Nagyon szerencsések vagyunk, hogy itt állnak meg hosszú, délre tartó útjuk előtt.": [
            "summer28_Demetrius"
      ],
      "Nem tudni, hogy miért vonzza őket a fény... nagyon érdekes.": [
            "summer28_Demetrius_sv1"
      ],
      "Kissé hideg van. Azt hiszem az ősz már itt van a sarkon.": [
            "summer28_Maru"
      ],
      "Azt hittem, hogy láttam valamit mozogni... valami nagyot és sötétet.": [
            "summer28_Sebastian"
      ],
      "Csak próbállak megijeszteni...": [
            "summer28_Sebastian_sv1"
      ],
      "Psszt... Majd nézz be holnap a boltba, hogy beszerezd az őszi magvakat!": [
            "summer28_Pierre"
      ],
      "Ugye milyen romantikusak ezek a gyertyák?": [
            "summer28_Caroline"
      ],
      "Majd idelopódzom, ha megérkeznek a medúzák... Senkit se akarok megzavarni.": [
            "summer28_Linus"
      ],
      "Nem hiszem el, hogy vége van a nyárnak... Úgy érzem, mintha csak most kezdődött volna.": [
            "summer28_Alex"
      ],
      "Mi az, miért nézel rám így? Azt hiszed túl öreg vagyok ahhoz, hogy ilyesmiket élvezzek?": [
            "summer28_George"
      ],
      "Emlékszem, mikor a medúzákat láttam, még kislány koromban. Ó, mennyire ugráltam örömömben, mikor megérkeztek!": [
            "summer28_Evelyn"
      ],
      "De ez már régen történt... Most már kevésbé vagyok tele energiával.": [
            "summer28_Evelyn_sv1"
      ],
      "Jó estét, @. A Holdfény medúzák közel járnak... Már láttam egyet világítani a messzeségben.": [
            "summer28_Lewis"
      ],
      "Amint elindítjuk a gyertya-hajót, bejönnek a kikötőbe üdvözölni minket.": [
            "summer28_Lewis_sv1"
      ],
      "Ma a spéci cipőmet vettem fel... De senki se vette észre.": [
            "summer28_Clint"
      ],
      "Nézz arrafelé, a végtelen tengerre. Mélyen a víz alatt mindenféle létforma mozog ide-oda a sötétben.": [
            "summer28_Emily"
      ],
      "Kísérteties, ugye?": [
            "summer28_Emily_sv1"
      ],
      "Az élet olyan könnyű a medúzáknak... csak hagyod, hogy a hullámok örökké tereljék utadat.": [
            "summer28_Penny"
      ],
      "Ne mondd el Gusnak, de kicsit csalódott vagyok, hogy ma nincs lakoma.": [
            "summer28_Pam"
      ],
      "Ha megérkeznek a medúzák akkor készítek róluk egy képet.": [
            "summer28_Haley"
      ],
      "Ott! Láttam valamit világítani!": [
            "summer28_Jodi"
      ],
      "Óh... Eltűnt.": [
            "summer28_Jodi_sv1"
      ],
      "Jó estét, @. Remélem ki tudsz majd kapcsolódni a nagy aratási szezon előtt.": [
            "summer28_Kent"
      ],
      "Vajon mérgezőek?": [
            "summer28_Sam"
      ],
      "Talán mégse kéne belöknöm Sebastiant a vízbe...": [
            "summer28_Sam_sv1"
      ],
      "Üdv. Épp tisztelgek egy ismételten elmúlt nyárnak.": [
            "summer28_Leah"
      ],
      "A medúzák egy éve is itt voltak, és egy év múlva ismét visszatérnek... a természet lenyűgöző.": [
            "summer28_Shane"
      ],
      "Túl nagy a tömeg súlya egy ilyen ősi, fából készült kikötőnek! Én itt maradok a strand környékén.": [
            "summer28_Marnie"
      ],
      "Ha folyton beszennyezzük az óceánokat, a medúzák idővel kihalnak. Ez a folyamat már elindult.": [
            "summer28_Elliott"
      ],
      "Milyen szégyenletes... az, hogy már nem tiszteljük a környezetünket.": [
            "summer28_Elliott_sv1"
      ],
      "'Holdfény medúzák'... Vajon milyen lehet az ízük?": [
            "summer28_Gus"
      ],
      "Persze sose próbálnám ki!": [
            "summer28_Gus_sv1"
      ],
      "Azt mondod, hogy odafent esik? *meghökken*": [
            "summer28_Dwarf",
            "summer28_Dwarf_y2"
      ],
      "Eső... Számunkra szinte rejtély. Egyesek közülünk egész életüket úgy élik le, hogy sose tapasztalják meg.": [
            "summer28_Dwarf_sv1",
            "summer28_Dwarf_y2_sv1"
      ],
      "Hogyan találtál meg engem? Azt hittem alaposan elbújtam.": [
            "summer28_Wizard"
      ],
      "Talán látnoki képességgel vagy megáldva.": [
            "summer28_Wizard_sv1"
      ],
      "Én a Lunalookat jöttem megnézni... vagyis a 'Holdfény medúzákat', ahogy ti nevezitek őket. Vízi létformák ellenére szokatlanul nagy mágikus aurájuk van.": [
            "summer28_Wizard_sv2"
      ],
      "Nos, vége a nyárnak. Hogy őszinte legyek boldogan intek búcsút ezeknek az átkozott szúnyogoknak!": [
            "summer28_Harvey"
      ],
      "Úgy hallottam, hogy odahaza esik. Ezért jöttél ide?": [
            "summer28_Sandy",
            "summer28_Sandy_y2"
      ],
      "Nekem valójában kissé hiányzik az eső...": [
            "summer28_Sandy_sv1"
      ],
      "Remélem idén lesznek kicsinyek!": [
            "summer28_Jas"
      ],
      "Látni akarom a ritka zöld medúzát!": [
            "summer28_Vincent"
      ],
      "A legtöbb éjszakai hal félne a fénytől... ezek elég furák.": [
            "summer28_Willy"
      ],
      "A holdfény medúzák régi barátaim... a szigethez is évente eljönnek.": [
            "summer28_Leo"
      ],
      "Hoztam egy takarót, ha netán később fáznánk.": [
            "summer28_Abigail_spouse_y2"
      ],
      "Egy csöppet kicsike, de biztos megoldjuk valahogy...": [
            "summer28_Abigail_spouse_y2_sv1"
      ],
      "Ajjj... Annyira romantikus, főleg a gyertyákkal.": [
            "summer28_Haley_spouse_y2"
      ],
      "Viszlát nyár...": [
            "summer28_Haley_spouse_y2_sv1"
      ],
      "Szerinted van elég időm arra, hogy elhozzam a teleszkópomat otthonról?": [
            "summer28_Maru_spouse_y2"
      ],
      "Hmm... talán nem. Ezt nem akarom kihagyni!": [
            "summer28_Maru_spouse_y2_sv1"
      ],
      "Hé, hát itt vagy!": [
            "summer28_Emily_spouse_y2"
      ],
      "Az óceán annyi titkot és csodát rejt. Valóban bámulatos.": [
            "summer28_Emily_spouse_y2_sv1"
      ],
      "Hoztam egy kis pezsgőt a főeseményre... Még nincs vége a nyárnak!": [
            "summer28_Leah_spouse_y2"
      ],
      "Ha tudtam volna, hogy ilyen hűvös lesz az idő, akkor hoztam volna magunknak egy kannányi teát!": [
            "summer28_Penny_spouse_y2"
      ],
      "Jelenleg egy kis időt töltök a családommal. Hamarosan találkozunk a kikötőben, oké?": [
            "summer28_Alex_spouse_y2"
      ],
      "Váó... ma nagyon jól nézel ki!0": [
            "summer28_Sam_spouse_y2"
      ],
      "Üdvözöllek, édesem! Bármelyik pillanatban felbukkanhatnak a medúzák... Sose unom meg!": [
            "summer28_Harvey_spouse_y2"
      ],
      "Készen állsz az őszre? Én igen...": [
            "summer28_Shane_spouse_y2"
      ],
      "He? Ó, vettem egy királyi adagnak való zacskós sütőtökös chipset. Vehetsz egyet, ha akarsz.": [
            "summer28_Shane_spouse_y2_sv1"
      ],
      "Emlékszem az első Holdfény medúzás fesztiválra, amire te is eljöttél.": [
            "summer28_Sebastian_spouse_y2"
      ],
      "Nem vetted észre, de én téged figyeltelek, mikor a medúzák előjöttek. Gyönyörű voltál abban a kék fényben...": [
            "summer28_Sebastian_spouse_y2_sv1"
      ],
      "Áh, épp azon tűnődtem, hogy mikor érkezel meg!": [
            "summer28_Elliott_spouse_y2"
      ],
      "Menjünk hamarosan a kikötőbe, és üdvözöljük a vízi vendégeinket!": [
            "summer28_Elliott_spouse_y2_sv1"
      ],
      "Úgy tűnik van egy ritka zöld medúza. Én akarok lenni az első, aki ma este látni fogja!": [
            "summer28_Abigail_y2"
      ],
      "Minden évben megvizsgálom a gyertya-hajót, és befoltozom az esetleges lyukait.": [
            "summer28_Robin_y2"
      ],
      "Képzeld el, ha a fesztivál közben elsüllyedne...": [
            "summer28_Robin_y2_sv1"
      ],
      "Van egy másfajta 'medúza', amit a horgászok néha kifognak a vízből. A nevük ellenére nagyon eltérő a természetük a Holdfény medúzákétól...": [
            "summer28_Demetrius_y2"
      ],
      "Látsz egy halvány ragyogást a horizonton? Azok biztos ők lesznek!": [
            "summer28_Maru_y2"
      ],
      "Ha belebámulsz az óceánba, van rá esély, hogy valami odalent visszabámul rád...": [
            "summer28_Sebastian_y2"
      ],
      "Észrevettem, hogy senki se használja ezt a kikötőt, szóval halkan ideosontam.": [
            "summer28_Linus_y2"
      ],
      "Én is szeretem a medúzákat bámulni.": [
            "summer28_Linus_y2_sv1"
      ],
      "Üdv, @ gazda. Gyere be holnap a boltba, hogy megvásárold az őszi magvaidat!": [
            "summer28_Pierre_y2"
      ],
      "Boldog vagyok, hogy a medúzák úgy döntöttek, hogy meglátogatnak minket déli útjukon. Ez egy varázslatos pillanat a közösségünk számára, amin együtt osztozkodhatunk.": [
            "summer28_Caroline_y2"
      ],
      "Kár, hogy a nyárnak véget kell érnie, de azt hiszem ilyen az élet...": [
            "summer28_Alex_y2"
      ],
      "A régi időkben begyűjtöttük és bepalackoztuk őket...": [
            "summer28_George_y2"
      ],
      "Hogy változnak az idők... hogy változnak az idők...": [
            "summer28_George_y2_sv1"
      ],
      "George és én már több évtizede együtt figyeljük a medúzákat jönni-menni.": [
            "summer28_Evelyn_y2"
      ],
      "Üdvözöllek @! Ahogy közeleg az este, a Holdfény medúzák egyre közelebb kerülnek a parthoz.": [
            "summer28_Lewis_y2"
      ],
      "Amint a gyertya-hajót útnak indítjuk, elkezdenek a kikötő körül gyülekezni.": [
            "summer28_Lewis_y2_sv1"
      ],
      "Túl közel kerültem egy hullámhoz, és most elázott a lábam...": [
            "summer28_Clint_y2"
      ],
      "Brr... elég hűvös az idő. Sapkát kellett volna felvennem!": [
            "summer28_Penny_y2"
      ],
      "Hé kölyök. Te egy gazda vagy. Mondd csak... tudsz zselét készíteni ezekből a dolgokból?": [
            "summer28_Pam_y2"
      ],
      "Jó sok pénzt spórolhatnék, ha azzal kenhetném be a pirítósomat!": [
            "summer28_Pam_y2_sv1"
      ],
      "A holdfény medúzáknak rejtélyes mélykék aurájuk van...": [
            "summer28_Emily_y2"
      ],
      "Több van bennük, mint ami látszik.": [
            "summer28_Emily_y2_sv1"
      ],
      "Nem volt időm kisminkelni magamat... Szerinted a sötétben ezt észreveszi majd valaki?": [
            "summer28_Haley_y2"
      ],
      "A telihold vezeti a medúzákat a partunkra.": [
            "summer28_Jodi_y2"
      ],
      "Hé. Nagy terveid vannak az őszre?": [
            "summer28_Kent_y2"
      ],
      "Lehet, hogy csak egy jó szemem maradt, de biztosíthatlak, hogy bármilyen sötétben ólálkodó ádáz lényt meglátok.": [
            "summer28_Marlon_y2"
      ],
      "Hamarosan véget ér a nyár. Hiányozni fognak a hosszabb nappalok!": [
            "summer28_Sam_y2"
      ],
      "Vannak mókás terveid az őszi szezonra? Hamarosan ki kell díszítenem a házamat.": [
            "summer28_Leah_y2"
      ],
      "Vajon idén hányan fognak eljönni?": [
            "summer28_Shane_y2"
      ],
      "Nem mehetek tovább a kikötőn. Reszketni tudok a recsegő fa hangjától.": [
            "summer28_Marnie_y2"
      ],
      "Mikor még kislány voltam, beszakadt alattam egy rothadó kikötő, és az mély nyomot hagyott bennem...": [
            "summer28_Marnie_y2_sv1"
      ],
      "A víz felszínén tündöklő gyertyafények egyszerűen lélegzetelállítóak. Olyan, mintha életre kelt volna egy festmény.": [
            "summer28_Elliott_y2"
      ],
      "*szimat* Áhh... az óceán friss illata mindig olyan kielégítő.": [
            "summer28_Gus_y2"
      ],
      "A Lunalook ragyogó tojásaiból hathatós reagens készíthető...": [
            "summer28_Wizard_y2"
      ],
      "Minden múló másodperccel egyre nő a várakozásom...": [
            "summer28_Harvey_y2"
      ],
      "Valójában nekem egy kicsit hiányzik az eső...": [
            "summer28_Sandy_y2_sv1"
      ],
      "Honnan tudják a medúzák, hogy merre ússzanak, ha nincs szemük?": [
            "summer28_Jas_y2"
      ],
      "Egyszer megérintettem egy medúzát és megcsípte a kezemet.": [
            "summer28_Vincent_y2"
      ],
      "Ez egy régi horgászati szabály... ha valaha kifognál egy holdfény medúzát, akkor vissza kell dobnod a tengerbe.": [
            "summer28_Willy_y2"
      ],
      "A régi otthoni barátaim hamarosan meglátogatnak minket!": [
            "summer28_Leo_y2"
      ]
}